[
    {
        "id" : 1,
        "name" : "111111.",
        "email" : "이메일1111ㅣ",
        "language" : "언어11111니다",
        "experience" : 1111111111111
    },
    {
        "id" : 2,
        "name" : "2222222.",
        "email" : "2222이메일입니다22",
        "language" : "언어2222222입니다",
        "experience" : 222222222
    },
    {
        "id" : 3,
        "name" : "333333333.",
        "email" : "이메일3333입ㄴ다ㅣ",
        "language" : "언어3333입니다",
        "experience" : 333333333
    },
    {
        "id" : 4,
        "name" : "4444444.",
        "email" : "이메일44444입ㄴ다ㅣ",
        "language" : "언어입44444니다",
        "experience" : 444444444
    }
]